invoice/__init__.py
invoice/invoice.py
django_invoice_library-0.1.0.dist-info/METADATA
django_invoice_library-0.1.0.dist-info/WHEEL
django_invoice_library-0.1.0.dist-info/top_level.txt
django_invoice_library-0.1.0.dist-info/RECORD
