Metadata-Version: 2.1
Name: django-invoice-library
Version: 0.1.0
Summary: A Django-based invoice generation library
Home-page: https://github.com/yourusername/django-invoice-library
Author: Your Name
Author-email: your.email@example.com
License: MIT
Platform: UNKNOWN
Classifier: Development Status :: 3 - Alpha
Classifier: Intended Audience :: Developers
Classifier: License :: OSI Approved :: MIT License
Classifier: Programming Language :: Python :: 3
Classifier: Framework :: Django
Requires-Dist: Django>=3.2
